setup.py
TalesParse/TalesParse.py
TalesParse.egg-info/PKG-INFO
TalesParse.egg-info/SOURCES.txt
TalesParse.egg-info/dependency_links.txt
TalesParse.egg-info/entry_points.txt
TalesParse.egg-info/requires.txt
TalesParse.egg-info/top_level.txt