Metadata-Version: 1.0
Name: TalesParse
Version: 1.0.0
Summary: Scraping good and bad tales.
Home-page: UNKNOWN
Author: UNKNOWN
Author-email: UNKNOWN
License: UNKNOWN
Platform: UNKNOWN
